{
    "indices": {
      "spx": "^GSPC",
      "sp500": "^GSPC",
      "sandp500": "^GSPC",
      "s&p": "^GSPC",
      "s&p500": "^GSPC",
      "s&p 500": "^GSPC",
      "sandp": "^GSPC",
      "s and p": "^GSPC",
      "s and p 500": "^GSPC",
  
      "dow": "^DJI",
      "dowjones": "^DJI",
      "djia": "^DJI",
      "dow jones": "^DJI",
      "dow jones industrial": "^DJI",
      "dow jones industrial average": "^DJI",
      "dow industrials": "^DJI",
      "dow industrial average": "^DJI",
  
      "nasdaq": "^IXIC",
      "nasdaq composite": "^IXIC",
      "nasdaq index": "^IXIC",
      "nasdaq composite index": "^IXIC",
  
      "nasdaq100": "^NDX",
      "ndx": "^NDX",
      "nasdaq 100": "^NDX",
      "nasdaq-100": "^NDX",
      "nasdaq100 index": "^NDX",
      "ndx index": "^NDX",
  
      "nifty": "^NSEI",
      "nifty50": "^NSEI",
      "nse50": "^NSEI",
      "nifty 50": "^NSEI",
      "nifty index": "^NSEI",
      "nifty 50 index": "^NSEI",
  
      "sensex": "^BSESN",
      "bse sensex": "^BSESN",
      "sensex index": "^BSESN",
      "bse sensex index": "^BSESN",
  
      "kse100": "^KSE",
      "kse": "^KSE",
      "kse100index": "^KSE",
      "kse 100": "^KSE",
      "kse-100": "^KSE",
      "kse 100 index": "^KSE",
      "pakistan kse": "^KSE",
      "pakistan kse 100": "^KSE",
      "pakistan kse100": "^KSE",
      "pakistan kse 100 index": "^KSE",
  
      "ftse": "^FTSE",
      "ftse100": "^FTSE",
      "ftse 100": "^FTSE",
      "ftse100 index": "^FTSE",
      "ftse 100 index": "^FTSE",
      "ftse index": "^FTSE",
  
      "dax": "^GDAXI",
      "dax index": "^GDAXI",
      "dax30": "^GDAXI",
      "dax 30": "^GDAXI",
      "german dax": "^GDAXI",
  
      "cac40": "^FCHI",
      "cac 40": "^FCHI",
      "cac 40 index": "^FCHI",
      "france cac40": "^FCHI",
      "cac index": "^FCHI",
  
      "nikkei": "^N225",
      "nikkei225": "^N225",
      "nikkei 225": "^N225",
      "nikkei index": "^N225",
      "nikkei 225 index": "^N225",
  
      "hangseng": "^HSI",
      "hsi": "^HSI",
      "hang seng": "^HSI",
      "hang seng index": "^HSI",
  
      "ssec": "^SSEC",
      "ssec index": "^SSEC",
      "shanghai composite": "^SSEC",
      "shanghai composite index": "^SSEC",
      "sse composite": "^SSEC",
      "sse composite index": "^SSEC",
  
      "asx200": "^AXJO",
      "asx 200": "^AXJO",
      "asx200 index": "^AXJO",
      "asx 200 index": "^AXJO",
      "aus200": "^AXJO",
      "aus 200": "^AXJO",
      "asx index": "^AXJO",
  
      "tsx": "^GSPTSE",
      "tsxcomp": "^GSPTSE",
      "tsx composite": "^GSPTSE",
      "tsx composite index": "^GSPTSE",
      "tsx60": "^GSPTSE",
      "tsx60 index": "^GSPTSE"
    }
  }